LICENSE
MANIFEST.in
README.md
popper.py
setup.py
popper/__init__.py
popper/asp.py
popper/constrain.py
popper/core.py
popper/cpsolver.py
popper/gen0.py
popper/gen1.py
popper/generate.py
popper/loop.py
popper/tester.py
popper/util.py
popper/lp/alan.pl
popper/lp/test.pl
popper/lp/test2.pl
popper_ilp.egg-info/PKG-INFO
popper_ilp.egg-info/SOURCES.txt
popper_ilp.egg-info/dependency_links.txt
popper_ilp.egg-info/requires.txt
popper_ilp.egg-info/top_level.txt