Metadata-Version: 2.1
Name: popper-ilp
Version: 1.1.0
Summary: Popper
Home-page: https://github.com/logic-and-learning-lab/Popper
Author: Andrew Cropper
Author-email: andrew.cropper@cs.ox.ac.uk
License: UNKNOWN
Platform: UNKNOWN
License-File: LICENSE
